btcget.py
btcget-0.0.5.dist-info/LICENSE
btcget-0.0.5.dist-info/METADATA
btcget-0.0.5.dist-info/WHEEL
btcget-0.0.5.dist-info/entry_points.txt
btcget-0.0.5.dist-info/top_level.txt
btcget-0.0.5.dist-info/RECORD
