Metadata-Version: 2.1
Name: btcget
Version: 0.0.5
Summary: Simple REST API wrapper for fetching Bitcoin market price data via multiple backends.
Home-page: https://github.com/j0021/btcget
Author: Joel Torres
Author-email: joel@torreshub.com
License: The Unlicense
Platform: any
Classifier: Development Status :: 4 - Beta
Classifier: Operating System :: OS Independent
Classifier: Intended Audience :: Developers
Classifier: Intended Audience :: Financial and Insurance Industry
Classifier: License :: OSI Approved :: The Unlicense (Unlicense)
Classifier: Programming Language :: Python :: 3
Classifier: Topic :: Internet :: WWW/HTTP
License-File: LICENSE
Requires-Dist: PyYAML ==6.0.1
Requires-Dist: requests ==2.31.0
